.gitignore
LICENSE
MANIFEST.in
Makefile
NEWS
README.md
setup.py
perfidy/__init__.py
perfidy/_dict.py
perfidy/_extras.py
perfidy/_func.py
perfidy/_hamt.py
perfidy.egg-info/PKG-INFO
perfidy.egg-info/SOURCES.txt
perfidy.egg-info/dependency_links.txt
perfidy.egg-info/top_level.txt
perfidy/tests/__init__.py
perfidy/tests/test_extras.py
perfidy/tests/test_func.py
perfidy/tests/test_mapping.py