Metadata-Version: 1.1
Name: perfidy
Version: 0.0.2
Summary: Useful extra bits for Python - things that shold be in the standard library
Home-page: https://github.com/jml/perfidy
Author: Perfidy authors
Author-email: testtools-dev@lists.launchpad.net
License: UNKNOWN
Platform: UNKNOWN
Classifier: License :: OSI Approved :: MIT License
